lionagi/__init__.py
lionagi/_class_registry.py
lionagi/_errors.py
lionagi/_types.py
lionagi/config.py
lionagi/fields.py
lionagi/py.typed
lionagi/utils.py
lionagi/version.py
lionagi/adapters/__init__.py
lionagi/adapters/_utils.py
lionagi/adapters/async_postgres_adapter.py
lionagi/libs/__init__.py
lionagi/libs/file/__init__.py
lionagi/libs/file/chunk.py
lionagi/libs/file/process.py
lionagi/libs/schema/__init__.py
lionagi/libs/schema/as_readable.py
lionagi/libs/schema/breakdown_pydantic_annotation.py
lionagi/libs/schema/extract_code_block.py
lionagi/libs/schema/extract_docstring.py
lionagi/libs/schema/function_to_schema.py
lionagi/libs/schema/load_pydantic_model_from_schema.py
lionagi/libs/schema/minimal_yaml.py
lionagi/libs/validate/__init__.py
lionagi/libs/validate/common_field_validators.py
lionagi/libs/validate/to_num.py
lionagi/libs/validate/validate_boolean.py
lionagi/ln/__init__.py
lionagi/ln/_async_call.py
lionagi/ln/_hash.py
lionagi/ln/_json_dump.py
lionagi/ln/_list_call.py
lionagi/ln/_to_list.py
lionagi/ln/_utils.py
lionagi/ln/types.py
lionagi/ln/concurrency/__init__.py
lionagi/ln/concurrency/_compat.py
lionagi/ln/concurrency/cancel.py
lionagi/ln/concurrency/errors.py
lionagi/ln/concurrency/patterns.py
lionagi/ln/concurrency/primitives.py
lionagi/ln/concurrency/resource_tracker.py
lionagi/ln/concurrency/task.py
lionagi/ln/concurrency/utils.py
lionagi/ln/fuzzy/__init__.py
lionagi/ln/fuzzy/_extract_json.py
lionagi/ln/fuzzy/_fuzzy_json.py
lionagi/ln/fuzzy/_fuzzy_match.py
lionagi/ln/fuzzy/_fuzzy_validate.py
lionagi/ln/fuzzy/_string_similarity.py
lionagi/ln/fuzzy/_to_dict.py
lionagi/models/__init__.py
lionagi/models/field_model.py
lionagi/models/hashable_model.py
lionagi/models/model_params.py
lionagi/models/operable_model.py
lionagi/models/schema_model.py
lionagi/operations/__init__.py
lionagi/operations/_visualize_graph.py
lionagi/operations/builder.py
lionagi/operations/fields.py
lionagi/operations/flow.py
lionagi/operations/manager.py
lionagi-0.18.1.dist-info/METADATA
lionagi-0.18.1.dist-info/WHEEL
lionagi-0.18.1.dist-info/licenses/LICENSE
lionagi-0.18.1.dist-info/RECORD
