Metadata-Version: 2.4
Name: lionagi
Version: 0.18.1
Summary: An Intelligence Operating System.
Author-email: HaiyangLi <quantocean.li@gmail.com>
License:            Apache License
License-File: LICENSE
Classifier: Framework :: Pydantic
Classifier: Framework :: Pydantic :: 2
Classifier: Framework :: Pytest
Classifier: Intended Audience :: Developers
Classifier: License :: OSI Approved :: Apache Software License
Classifier: Operating System :: OS Independent
Classifier: Programming Language :: Python :: 3
Classifier: Programming Language :: Python :: 3 :: Only
Classifier: Programming Language :: Python :: 3.10
Classifier: Programming Language :: Python :: 3.11
Classifier: Programming Language :: Python :: 3.12
Classifier: Programming Language :: Python :: 3.13
Requires-Python: >=3.10
Requires-Dist: aiocache>=0.12.0
Requires-Dist: aiohttp>=3.11.0
Requires-Dist: anyio>=4.7.0
Requires-Dist: backoff>=2.0.0
Requires-Dist: json-repair>=0.40.0
Requires-Dist: msgspec>=0.18.0
Requires-Dist: pydantic-settings>=2.8.0
Requires-Dist: pydantic>=2.8.0
Requires-Dist: pydapter[pandas]>=1.2.0
Requires-Dist: python-dotenv>=1.1.0
Requires-Dist: tiktoken>=0.9.0
Provides-Extra: all
Requires-Dist: aiosqlite>=0.21.0; extra == 'all'
Requires-Dist: datamodel-code-generator>=0.31.2; extra == 'all'
Requires-Dist: docling>=2.15.0; extra == 'all'
Requires-Dist: fastmcp>=2.10.5; extra == 'all'
Requires-Dist: matplotlib>=3.7.0; extra == 'all'
Requires-Dist: networkx>=3.0.0; extra == 'all'
Requires-Dist: ollama>=0.4.0; extra == 'all'
Requires-Dist: pydapter[postgres]; extra == 'all'
Requires-Dist: rich>=13.0.0; extra == 'all'
Requires-Dist: xmltodict>=0.12.0; extra == 'all'
Provides-Extra: graph
Requires-Dist: matplotlib>=3.7.0; extra == 'graph'
Requires-Dist: networkx>=3.0.0; extra == 'graph'
Provides-Extra: mcp
Requires-Dist: fastmcp>=2.10.5; extra == 'mcp'
Provides-Extra: ollama
Requires-Dist: ollama>=0.4.0; extra == 'ollama'
Provides-Extra: postgres
Requires-Dist: pydapter[postgres]; extra == 'postgres'
Provides-Extra: reader
Requires-Dist: docling>=2.15.0; extra == 'reader'
Provides-Extra: rich
Requires-Dist: rich>=13.0.0; extra == 'rich'
Provides-Extra: schema
Requires-Dist: datamodel-code-generator>=0.31.2; extra == 'schema'
Provides-Extra: sqlite
Requires-Dist: aiosqlite>=0.21.0; extra == 'sqlite'
Provides-Extra: xml
Requires-Dist: xmltodict>=0.12.0; extra == 'xml'
